trytond/modules/account_invoice_line_twocolumn/README.rst
trytond/modules/account_invoice_line_twocolumn/__init__.py
trytond/modules/account_invoice_line_twocolumn/invoice.fodt
trytond/modules/account_invoice_line_twocolumn/invoiceline.py
trytond/modules/account_invoice_line_twocolumn/invoiceline.xml
trytond/modules/account_invoice_line_twocolumn/tryton.cfg
trytond/modules/account_invoice_line_twocolumn/versiondep.txt
trytond/modules/account_invoice_line_twocolumn/locale/de.po
trytond/modules/account_invoice_line_twocolumn/locale/en.po
trytond/modules/account_invoice_line_twocolumn/tests/__init__.py
trytond/modules/account_invoice_line_twocolumn/tests/test_invoice.py
trytond/modules/account_invoice_line_twocolumn/view/invoice_line_form.xml
mds_account_invoice_line_twocolumn-5.0.0.dist-info/METADATA
mds_account_invoice_line_twocolumn-5.0.0.dist-info/WHEEL
mds_account_invoice_line_twocolumn-5.0.0.dist-info/entry_points.txt
mds_account_invoice_line_twocolumn-5.0.0.dist-info/top_level.txt
mds_account_invoice_line_twocolumn-5.0.0.dist-info/RECORD
